grpclib/__init__.py
grpclib/_registry.py
grpclib/_typing.py
grpclib/client.py
grpclib/config.py
grpclib/const.py
grpclib/events.py
grpclib/exceptions.py
grpclib/metadata.py
grpclib/protocol.py
grpclib/py.typed
grpclib/server.py
grpclib/stream.py
grpclib/testing.py
grpclib/utils.py
grpclib/channelz/__init__.py
grpclib/channelz/service.py
grpclib/channelz/v1/__init__.py
grpclib/channelz/v1/channelz_grpc.py
grpclib/channelz/v1/channelz_pb2.py
grpclib/channelz/v1/channelz_pb2.pyi
grpclib/encoding/__init__.py
grpclib/encoding/base.py
grpclib/encoding/proto.py
grpclib/health/__init__.py
grpclib/health/check.py
grpclib/health/service.py
grpclib/health/v1/__init__.py
grpclib/health/v1/health_grpc.py
grpclib/health/v1/health_pb2.py
grpclib/health/v1/health_pb2.pyi
grpclib/plugin/__init__.py
grpclib/plugin/main.py
grpclib/reflection/__init__.py
grpclib/reflection/_deprecated.py
grpclib/reflection/service.py
grpclib/reflection/v1/__init__.py
grpclib/reflection/v1/reflection_grpc.py
grpclib/reflection/v1/reflection_pb2.py
grpclib/reflection/v1/reflection_pb2.pyi
grpclib/reflection/v1alpha/__init__.py
grpclib/reflection/v1alpha/reflection_grpc.py
grpclib/reflection/v1alpha/reflection_pb2.py
grpclib/reflection/v1alpha/reflection_pb2.pyi
grpclib-0.4.8.dist-info/LICENSE.txt
grpclib-0.4.8.dist-info/METADATA
grpclib-0.4.8.dist-info/WHEEL
grpclib-0.4.8.dist-info/entry_points.txt
grpclib-0.4.8.dist-info/top_level.txt
grpclib-0.4.8.dist-info/RECORD
